<?xml version="1.0" encoding="ISO-8859-1"?>
<nf:rpc-reply xmlns="http://www.cisco.com/nxos:1.0:ip" xmlns:nf="urn:ietf:params:xml:ns:netconf:base:1.0">
 <nf:data>
  <show>
   <ip>
    <interface>
     <__XML__BLK_Cmd_ip_show_interface_command_brief>
      <__XML__OPT_Cmd_ip_show_interface_command_operational>
       <__XML__OPT_Cmd_ip_show_interface_command_vrf>
        <__XML__OPT_Cmd_ip_show_interface_command___readonly__>
         <__readonly__>
          <TABLE_vrf>
           <ROW_vrf>
            <vrf-name-out>default</vrf-name-out>
           </ROW_vrf>
          </TABLE_vrf>
          <TABLE_intf>
           <ROW_intf>
            <intf-name>Vlan20</intf-name>
            <proto-state>up</proto-state>
            <link-state>up</link-state>
            <admin-state>up</admin-state>
            <iod>121</iod>
            <prefix>10.82.28.28</prefix>
            <subnet>10.82.28.28</subnet>
            <masklen>31</masklen>
            <num-addr>1</num-addr>
            <ip-disabled>FALSE</ip-disabled>
            <bcast-addr>255.255.255.255</bcast-addr>
            <num-maddr>0</num-maddr>
            <mtu>1500</mtu>
            <pref>0</pref>
            <tag>0</tag>
            <proxy-arp>disabled</proxy-arp>
            <lcl-proxy-arp>disabled</lcl-proxy-arp>
            <mrouting>disabled</mrouting>
            <icmp-redirect>disabled</icmp-redirect>
            <dir-bcast>disabled</dir-bcast>
            <ip-unreach>disabled</ip-unreach>
            <port-unreach>enabled</port-unreach>
            <urpf-mode>none</urpf-mode>
            <ip-ls-type>none</ip-ls-type>
            <stats-last-reset>never</stats-last-reset>
            <upkt-sent>37</upkt-sent>
            <upkt-recv>587</upkt-recv>
            <upkt-fwd>2</upkt-fwd>
            <upkt-orig>35</upkt-orig>
            <upkt-consumed>557</upkt-consumed>
            <ubyte-sent>5201</ubyte-sent>
            <ubyte-recv>38049</ubyte-recv>
            <ubyte-fwd>1631</ubyte-fwd>
            <ubyte-orig>3570</ubyte-orig>
            <ubyte-consumed>35269</ubyte-consumed>
            <mpkt-sent>0</mpkt-sent>
            <mpkt-recv>0</mpkt-recv>
            <mpkt-fwd>0</mpkt-fwd>
            <mpkt-orig>0</mpkt-orig>
            <mpkt-consumed>0</mpkt-consumed>
            <mbyte-sent>0</mbyte-sent>
            <mbyte-recv>0</mbyte-recv>
            <mbyte-fwd>0</mbyte-fwd>
            <mbyte-orig>0</mbyte-orig>
            <mbyte-consumed>0</mbyte-consumed>
            <bpkt-sent>0</bpkt-sent>
            <bpkt-recv>0</bpkt-recv>
            <bpkt-fwd>0</bpkt-fwd>
            <bpkt-orig>0</bpkt-orig>
            <bpkt-consumed>0</bpkt-consumed>
            <bbyte-sent>0</bbyte-sent>
            <bbyte-recv>0</bbyte-recv>
            <bbyte-fwd>0</bbyte-fwd>
            <bbyte-orig>0</bbyte-orig>
            <bbyte-consumed>0</bbyte-consumed>
            <lpkt-sent>0</lpkt-sent>
            <lpkt-recv>0</lpkt-recv>
            <lpkt-fwd>0</lpkt-fwd>
            <lpkt-orig>0</lpkt-orig>
            <lpkt-consumed>0</lpkt-consumed>
            <lbyte-sent>0</lbyte-sent>
            <lbyte-recv>0</lbyte-recv>
            <lbyte-fwd>0</lbyte-fwd>
            <lbyte-orig>0</lbyte-orig>
            <lbyte-consumed>0</lbyte-consumed>
           </ROW_intf>
          </TABLE_intf>
          <TABLE_vrf>
           <ROW_vrf>
            <vrf-name-out>default</vrf-name-out>
           </ROW_vrf>
          </TABLE_vrf>
          <TABLE_intf>
           <ROW_intf>
            <intf-name>Vlan207</intf-name>
            <proto-state>up</proto-state>
            <link-state>up</link-state>
            <admin-state>up</admin-state>
            <iod>130</iod>
            <prefix>134.6.255.66</prefix>
            <subnet>134.6.255.64</subnet>
            <masklen>29</masklen>
            <num-addr>1</num-addr>
            <ip-disabled>FALSE</ip-disabled>
            <bcast-addr>255.255.255.255</bcast-addr>
            <TABLE_maddr>
             <ROW_maddr>
              <maddr>224.0.0.102</maddr>
             </ROW_maddr>
            </TABLE_maddr>
            <num-maddr>1</num-maddr>
            <mtu>1500</mtu>
            <pref>0</pref>
            <tag>0</tag>
            <proxy-arp>disabled</proxy-arp>
            <lcl-proxy-arp>disabled</lcl-proxy-arp>
            <mrouting>disabled</mrouting>
            <icmp-redirect>disabled</icmp-redirect>
            <dir-bcast>disabled</dir-bcast>
            <ip-unreach>disabled</ip-unreach>
            <port-unreach>enabled</port-unreach>
            <urpf-mode>none</urpf-mode>
            <ip-ls-type>none</ip-ls-type>
            <stats-last-reset>never</stats-last-reset>
            <upkt-sent>11</upkt-sent>
            <upkt-recv>12</upkt-recv>
            <upkt-fwd>0</upkt-fwd>
            <upkt-orig>11</upkt-orig>
            <upkt-consumed>24</upkt-consumed>
            <ubyte-sent>1122</ubyte-sent>
            <ubyte-recv>1008</ubyte-recv>
            <ubyte-fwd>0</ubyte-fwd>
            <ubyte-orig>1122</ubyte-orig>
            <ubyte-consumed>2016</ubyte-consumed>
            <mpkt-sent>0</mpkt-sent>
            <mpkt-recv>9475242</mpkt-recv>
            <mpkt-fwd>0</mpkt-fwd>
            <mpkt-orig>0</mpkt-orig>
            <mpkt-consumed>18950484</mpkt-consumed>
            <mbyte-sent>0</mbyte-sent>
            <mbyte-recv>947524200</mbyte-recv>
            <mbyte-fwd>0</mbyte-fwd>
            <mbyte-orig>0</mbyte-orig>
            <mbyte-consumed>947524200</mbyte-consumed>
            <bpkt-sent>0</bpkt-sent>
            <bpkt-recv>0</bpkt-recv>
            <bpkt-fwd>0</bpkt-fwd>
            <bpkt-orig>0</bpkt-orig>
            <bpkt-consumed>0</bpkt-consumed>
            <bbyte-sent>0</bbyte-sent>
            <bbyte-recv>0</bbyte-recv>
            <bbyte-fwd>0</bbyte-fwd>
            <bbyte-orig>0</bbyte-orig>
            <bbyte-consumed>0</bbyte-consumed>
            <lpkt-sent>0</lpkt-sent>
            <lpkt-recv>0</lpkt-recv>
            <lpkt-fwd>0</lpkt-fwd>
            <lpkt-orig>0</lpkt-orig>
            <lpkt-consumed>0</lpkt-consumed>
            <lbyte-sent>0</lbyte-sent>
            <lbyte-recv>0</lbyte-recv>
            <lbyte-fwd>0</lbyte-fwd>
            <lbyte-orig>0</lbyte-orig>
            <lbyte-consumed>0</lbyte-consumed>
           </ROW_intf>
          </TABLE_intf>
          <TABLE_vrf>
           <ROW_vrf>
            <vrf-name-out>default</vrf-name-out>
           </ROW_vrf>
          </TABLE_vrf>
          <TABLE_intf>
           <ROW_intf>
            <intf-name>Vlan651</intf-name>
            <proto-state>up</proto-state>
            <link-state>up</link-state>
            <admin-state>up</admin-state>
            <iod>122</iod>
            <prefix>10.82.28.153</prefix>
            <subnet>10.82.28.152</subnet>
            <masklen>30</masklen>
            <num-addr>1</num-addr>
            <ip-disabled>FALSE</ip-disabled>
            <bcast-addr>255.255.255.255</bcast-addr>
            <num-maddr>0</num-maddr>
            <mtu>1500</mtu>
            <pref>0</pref>
            <tag>65100</tag>
            <proxy-arp>disabled</proxy-arp>
            <lcl-proxy-arp>disabled</lcl-proxy-arp>
            <mrouting>disabled</mrouting>
            <icmp-redirect>disabled</icmp-redirect>
            <dir-bcast>disabled</dir-bcast>
            <ip-unreach>disabled</ip-unreach>
            <port-unreach>enabled</port-unreach>
            <urpf-mode>none</urpf-mode>
            <ip-ls-type>none</ip-ls-type>
            <stats-last-reset>never</stats-last-reset>
            <upkt-sent>374</upkt-sent>
            <upkt-recv>190</upkt-recv>
            <upkt-fwd>130</upkt-fwd>
            <upkt-orig>244</upkt-orig>
            <upkt-consumed>566</upkt-consumed>
            <ubyte-sent>24148</ubyte-sent>
            <ubyte-recv>11358</ubyte-recv>
            <ubyte-fwd>5980</ubyte-fwd>
            <ubyte-orig>18168</ubyte-orig>
            <ubyte-consumed>35376</ubyte-consumed>
            <mpkt-sent>0</mpkt-sent>
            <mpkt-recv>0</mpkt-recv>
            <mpkt-fwd>0</mpkt-fwd>
            <mpkt-orig>0</mpkt-orig>
            <mpkt-consumed>0</mpkt-consumed>
            <mbyte-sent>0</mbyte-sent>
            <mbyte-recv>0</mbyte-recv>
            <mbyte-fwd>0</mbyte-fwd>
            <mbyte-orig>0</mbyte-orig>
            <mbyte-consumed>0</mbyte-consumed>
            <bpkt-sent>0</bpkt-sent>
            <bpkt-recv>0</bpkt-recv>
            <bpkt-fwd>0</bpkt-fwd>
            <bpkt-orig>0</bpkt-orig>
            <bpkt-consumed>0</bpkt-consumed>
            <bbyte-sent>0</bbyte-sent>
            <bbyte-recv>0</bbyte-recv>
            <bbyte-fwd>0</bbyte-fwd>
            <bbyte-orig>0</bbyte-orig>
            <bbyte-consumed>0</bbyte-consumed>
            <lpkt-sent>0</lpkt-sent>
            <lpkt-recv>0</lpkt-recv>
            <lpkt-fwd>0</lpkt-fwd>
            <lpkt-orig>0</lpkt-orig>
            <lpkt-consumed>0</lpkt-consumed>
            <lbyte-sent>0</lbyte-sent>
            <lbyte-recv>0</lbyte-recv>
            <lbyte-fwd>0</lbyte-fwd>
            <lbyte-orig>0</lbyte-orig>
            <lbyte-consumed>0</lbyte-consumed>
           </ROW_intf>
          </TABLE_intf>
          <TABLE_vrf>
           <ROW_vrf>
            <vrf-name-out>default</vrf-name-out>
           </ROW_vrf>
          </TABLE_vrf>
          <TABLE_intf>
           <ROW_intf>
            <intf-name>Vlan655</intf-name>
            <proto-state>up</proto-state>
            <link-state>up</link-state>
            <admin-state>up</admin-state>
            <iod>125</iod>
            <prefix>10.82.28.177</prefix>
            <subnet>10.82.28.176</subnet>
            <masklen>30</masklen>
            <num-addr>1</num-addr>
            <ip-disabled>FALSE</ip-disabled>
            <bcast-addr>255.255.255.255</bcast-addr>
            <num-maddr>0</num-maddr>
            <mtu>1500</mtu>
            <pref>0</pref>
            <tag>65100</tag>
            <proxy-arp>disabled</proxy-arp>
            <lcl-proxy-arp>disabled</lcl-proxy-arp>
            <mrouting>disabled</mrouting>
            <icmp-redirect>disabled</icmp-redirect>
            <dir-bcast>disabled</dir-bcast>
            <ip-unreach>disabled</ip-unreach>
            <port-unreach>enabled</port-unreach>
            <urpf-mode>none</urpf-mode>
            <ip-ls-type>none</ip-ls-type>
            <stats-last-reset>never</stats-last-reset>
            <upkt-sent>342879</upkt-sent>
            <upkt-recv>39</upkt-recv>
            <upkt-fwd>12</upkt-fwd>
            <upkt-orig>342887</upkt-orig>
            <upkt-consumed>95</upkt-consumed>
            <ubyte-sent>25372343</ubyte-sent>
            <ubyte-recv>3068</ubyte-recv>
            <ubyte-fwd>813</ubyte-fwd>
            <ubyte-orig>25373210</ubyte-orig>
            <ubyte-consumed>7660</ubyte-consumed>
            <mpkt-sent>0</mpkt-sent>
            <mpkt-recv>0</mpkt-recv>
            <mpkt-fwd>0</mpkt-fwd>
            <mpkt-orig>0</mpkt-orig>
            <mpkt-consumed>0</mpkt-consumed>
            <mbyte-sent>0</mbyte-sent>
            <mbyte-recv>0</mbyte-recv>
            <mbyte-fwd>0</mbyte-fwd>
            <mbyte-orig>0</mbyte-orig>
            <mbyte-consumed>0</mbyte-consumed>
            <bpkt-sent>0</bpkt-sent>
            <bpkt-recv>0</bpkt-recv>
            <bpkt-fwd>0</bpkt-fwd>
            <bpkt-orig>0</bpkt-orig>
            <bpkt-consumed>0</bpkt-consumed>
            <bbyte-sent>0</bbyte-sent>
            <bbyte-recv>0</bbyte-recv>
            <bbyte-fwd>0</bbyte-fwd>
            <bbyte-orig>0</bbyte-orig>
            <bbyte-consumed>0</bbyte-consumed>
            <lpkt-sent>0</lpkt-sent>
            <lpkt-recv>0</lpkt-recv>
            <lpkt-fwd>0</lpkt-fwd>
            <lpkt-orig>0</lpkt-orig>
            <lpkt-consumed>0</lpkt-consumed>
            <lbyte-sent>0</lbyte-sent>
            <lbyte-recv>0</lbyte-recv>
            <lbyte-fwd>0</lbyte-fwd>
            <lbyte-orig>0</lbyte-orig>
            <lbyte-consumed>0</lbyte-consumed>
           </ROW_intf>
          </TABLE_intf>
          <TABLE_vrf>
           <ROW_vrf>
            <vrf-name-out>default</vrf-name-out>
           </ROW_vrf>
          </TABLE_vrf>
          <TABLE_intf>
           <ROW_intf>
            <intf-name>Vlan901</intf-name>
            <proto-state>up</proto-state>
            <link-state>up</link-state>
            <admin-state>up</admin-state>
            <iod>119</iod>
            <prefix>10.82.29.1</prefix>
            <subnet>10.82.29.0</subnet>
            <masklen>29</masklen>
            <num-addr>1</num-addr>
            <ip-disabled>FALSE</ip-disabled>
            <bcast-addr>255.255.255.255</bcast-addr>
            <num-maddr>0</num-maddr>
            <mtu>1500</mtu>
            <pref>0</pref>
            <tag>65100</tag>
            <proxy-arp>disabled</proxy-arp>
            <lcl-proxy-arp>disabled</lcl-proxy-arp>
            <mrouting>disabled</mrouting>
            <icmp-redirect>disabled</icmp-redirect>
            <dir-bcast>disabled</dir-bcast>
            <ip-unreach>disabled</ip-unreach>
            <port-unreach>enabled</port-unreach>
            <urpf-mode>none</urpf-mode>
            <ip-ls-type>none</ip-ls-type>
            <stats-last-reset>never</stats-last-reset>
            <upkt-sent>1379642</upkt-sent>
            <upkt-recv>1379391</upkt-recv>
            <upkt-fwd>1375367</upkt-fwd>
            <upkt-orig>4285</upkt-orig>
            <upkt-consumed>8232</upkt-consumed>
            <ubyte-sent>121031798</ubyte-sent>
            <ubyte-recv>96156285</ubyte-recv>
            <ubyte-fwd>120597336</ubyte-fwd>
            <ubyte-orig>435302</ubyte-orig>
            <ubyte-consumed>691488</ubyte-consumed>
            <mpkt-sent>0</mpkt-sent>
            <mpkt-recv>0</mpkt-recv>
            <mpkt-fwd>0</mpkt-fwd>
            <mpkt-orig>0</mpkt-orig>
            <mpkt-consumed>0</mpkt-consumed>
            <mbyte-sent>0</mbyte-sent>
            <mbyte-recv>0</mbyte-recv>
            <mbyte-fwd>0</mbyte-fwd>
            <mbyte-orig>0</mbyte-orig>
            <mbyte-consumed>0</mbyte-consumed>
            <bpkt-sent>0</bpkt-sent>
            <bpkt-recv>0</bpkt-recv>
            <bpkt-fwd>0</bpkt-fwd>
            <bpkt-orig>0</bpkt-orig>
            <bpkt-consumed>0</bpkt-consumed>
            <bbyte-sent>0</bbyte-sent>
            <bbyte-recv>0</bbyte-recv>
            <bbyte-fwd>0</bbyte-fwd>
            <bbyte-orig>0</bbyte-orig>
            <bbyte-consumed>0</bbyte-consumed>
            <lpkt-sent>0</lpkt-sent>
            <lpkt-recv>0</lpkt-recv>
            <lpkt-fwd>0</lpkt-fwd>
            <lpkt-orig>0</lpkt-orig>
            <lpkt-consumed>0</lpkt-consumed>
            <lbyte-sent>0</lbyte-sent>
            <lbyte-recv>0</lbyte-recv>
            <lbyte-fwd>0</lbyte-fwd>
            <lbyte-orig>0</lbyte-orig>
            <lbyte-consumed>0</lbyte-consumed>
           </ROW_intf>
          </TABLE_intf>
          <TABLE_vrf>
           <ROW_vrf>
            <vrf-name-out>default</vrf-name-out>
           </ROW_vrf>
          </TABLE_vrf>
          <TABLE_intf>
           <ROW_intf>
            <intf-name>Vlan951</intf-name>
            <proto-state>up</proto-state>
            <link-state>up</link-state>
            <admin-state>up</admin-state>
            <iod>129</iod>
            <prefix>10.82.28.35</prefix>
            <subnet>10.82.28.34</subnet>
            <masklen>31</masklen>
            <num-addr>1</num-addr>
            <ip-disabled>FALSE</ip-disabled>
            <bcast-addr>255.255.255.255</bcast-addr>
            <num-maddr>0</num-maddr>
            <mtu>1500</mtu>
            <pref>0</pref>
            <tag>65100</tag>
            <proxy-arp>disabled</proxy-arp>
            <lcl-proxy-arp>disabled</lcl-proxy-arp>
            <mrouting>disabled</mrouting>
            <icmp-redirect>disabled</icmp-redirect>
            <dir-bcast>disabled</dir-bcast>
            <ip-unreach>disabled</ip-unreach>
            <port-unreach>enabled</port-unreach>
            <urpf-mode>none</urpf-mode>
            <ip-ls-type>none</ip-ls-type>
            <stats-last-reset>never</stats-last-reset>
            <upkt-sent>15</upkt-sent>
            <upkt-recv>830</upkt-recv>
            <upkt-fwd>0</upkt-fwd>
            <upkt-orig>15</upkt-orig>
            <upkt-consumed>20</upkt-consumed>
            <ubyte-sent>1390</ubyte-sent>
            <ubyte-recv>417403</ubyte-recv>
            <ubyte-fwd>0</ubyte-fwd>
            <ubyte-orig>1390</ubyte-orig>
            <ubyte-consumed>1680</ubyte-consumed>
            <mpkt-sent>0</mpkt-sent>
            <mpkt-recv>3661260</mpkt-recv>
            <mpkt-fwd>0</mpkt-fwd>
            <mpkt-orig>0</mpkt-orig>
            <mpkt-consumed>0</mpkt-consumed>
            <mbyte-sent>0</mbyte-sent>
            <mbyte-recv>219762533</mbyte-recv>
            <mbyte-fwd>0</mbyte-fwd>
            <mbyte-orig>0</mbyte-orig>
            <mbyte-consumed>0</mbyte-consumed>
            <bpkt-sent>0</bpkt-sent>
            <bpkt-recv>0</bpkt-recv>
            <bpkt-fwd>0</bpkt-fwd>
            <bpkt-orig>0</bpkt-orig>
            <bpkt-consumed>0</bpkt-consumed>
            <bbyte-sent>0</bbyte-sent>
            <bbyte-recv>0</bbyte-recv>
            <bbyte-fwd>0</bbyte-fwd>
            <bbyte-orig>0</bbyte-orig>
            <bbyte-consumed>0</bbyte-consumed>
            <lpkt-sent>0</lpkt-sent>
            <lpkt-recv>0</lpkt-recv>
            <lpkt-fwd>0</lpkt-fwd>
            <lpkt-orig>0</lpkt-orig>
            <lpkt-consumed>0</lpkt-consumed>
            <lbyte-sent>0</lbyte-sent>
            <lbyte-recv>0</lbyte-recv>
            <lbyte-fwd>0</lbyte-fwd>
            <lbyte-orig>0</lbyte-orig>
            <lbyte-consumed>0</lbyte-consumed>
           </ROW_intf>
          </TABLE_intf>
          <TABLE_vrf>
           <ROW_vrf>
            <vrf-name-out>default</vrf-name-out>
           </ROW_vrf>
          </TABLE_vrf>
          <TABLE_intf>
           <ROW_intf>
            <intf-name>loopback0</intf-name>
            <proto-state>up</proto-state>
            <link-state>up</link-state>
            <admin-state>up</admin-state>
            <iod>120</iod>
            <prefix>10.82.31.15</prefix>
            <subnet>10.82.31.15</subnet>
            <masklen>32</masklen>
            <num-addr>1</num-addr>
            <ip-disabled>FALSE</ip-disabled>
            <bcast-addr>255.255.255.255</bcast-addr>
            <num-maddr>0</num-maddr>
            <mtu>1500</mtu>
            <pref>0</pref>
            <tag>65100</tag>
            <proxy-arp>disabled</proxy-arp>
            <lcl-proxy-arp>disabled</lcl-proxy-arp>
            <mrouting>disabled</mrouting>
            <icmp-redirect>enabled</icmp-redirect>
            <dir-bcast>disabled</dir-bcast>
            <ip-unreach>disabled</ip-unreach>
            <port-unreach>enabled</port-unreach>
            <urpf-mode>none</urpf-mode>
            <ip-ls-type>none</ip-ls-type>
            <stats-last-reset>never</stats-last-reset>
            <upkt-sent>0</upkt-sent>
            <upkt-recv>0</upkt-recv>
            <upkt-fwd>0</upkt-fwd>
            <upkt-orig>0</upkt-orig>
            <upkt-consumed>1555</upkt-consumed>
            <ubyte-sent>0</ubyte-sent>
            <ubyte-recv>0</ubyte-recv>
            <ubyte-fwd>0</ubyte-fwd>
            <ubyte-orig>0</ubyte-orig>
            <ubyte-consumed>93005</ubyte-consumed>
            <mpkt-sent>0</mpkt-sent>
            <mpkt-recv>0</mpkt-recv>
            <mpkt-fwd>0</mpkt-fwd>
            <mpkt-orig>0</mpkt-orig>
            <mpkt-consumed>0</mpkt-consumed>
            <mbyte-sent>0</mbyte-sent>
            <mbyte-recv>0</mbyte-recv>
            <mbyte-fwd>0</mbyte-fwd>
            <mbyte-orig>0</mbyte-orig>
            <mbyte-consumed>0</mbyte-consumed>
            <bpkt-sent>0</bpkt-sent>
            <bpkt-recv>0</bpkt-recv>
            <bpkt-fwd>0</bpkt-fwd>
            <bpkt-orig>0</bpkt-orig>
            <bpkt-consumed>0</bpkt-consumed>
            <bbyte-sent>0</bbyte-sent>
            <bbyte-recv>0</bbyte-recv>
            <bbyte-fwd>0</bbyte-fwd>
            <bbyte-orig>0</bbyte-orig>
            <bbyte-consumed>0</bbyte-consumed>
            <lpkt-sent>0</lpkt-sent>
            <lpkt-recv>0</lpkt-recv>
            <lpkt-fwd>0</lpkt-fwd>
            <lpkt-orig>0</lpkt-orig>
            <lpkt-consumed>0</lpkt-consumed>
            <lbyte-sent>0</lbyte-sent>
            <lbyte-recv>0</lbyte-recv>
            <lbyte-fwd>0</lbyte-fwd>
            <lbyte-orig>0</lbyte-orig>
            <lbyte-consumed>0</lbyte-consumed>
           </ROW_intf>
          </TABLE_intf>
          <TABLE_vrf>
           <ROW_vrf>
            <vrf-name-out>default</vrf-name-out>
           </ROW_vrf>
          </TABLE_vrf>
          <TABLE_intf>
           <ROW_intf>
            <intf-name>Ethernet1/10</intf-name>
            <proto-state>up</proto-state>
            <link-state>up</link-state>
            <admin-state>up</admin-state>
            <iod>15</iod>
            <prefix>10.82.28.193</prefix>
            <subnet>10.82.28.192</subnet>
            <masklen>30</masklen>
            <num-addr>1</num-addr>
            <ip-disabled>FALSE</ip-disabled>
            <bcast-addr>255.255.255.255</bcast-addr>
            <num-maddr>0</num-maddr>
            <mtu>1500</mtu>
            <pref>0</pref>
            <tag>65100</tag>
            <proxy-arp>disabled</proxy-arp>
            <lcl-proxy-arp>disabled</lcl-proxy-arp>
            <mrouting>disabled</mrouting>
            <icmp-redirect>enabled</icmp-redirect>
            <dir-bcast>disabled</dir-bcast>
            <ip-unreach>disabled</ip-unreach>
            <port-unreach>enabled</port-unreach>
            <urpf-mode>none</urpf-mode>
            <ip-ls-type>none</ip-ls-type>
            <stats-last-reset>never</stats-last-reset>
            <upkt-sent>0</upkt-sent>
            <upkt-recv>0</upkt-recv>
            <upkt-fwd>0</upkt-fwd>
            <upkt-orig>0</upkt-orig>
            <upkt-consumed>0</upkt-consumed>
            <ubyte-sent>0</ubyte-sent>
            <ubyte-recv>0</ubyte-recv>
            <ubyte-fwd>0</ubyte-fwd>
            <ubyte-orig>0</ubyte-orig>
            <ubyte-consumed>0</ubyte-consumed>
            <mpkt-sent>0</mpkt-sent>
            <mpkt-recv>0</mpkt-recv>
            <mpkt-fwd>0</mpkt-fwd>
            <mpkt-orig>0</mpkt-orig>
            <mpkt-consumed>0</mpkt-consumed>
            <mbyte-sent>0</mbyte-sent>
            <mbyte-recv>0</mbyte-recv>
            <mbyte-fwd>0</mbyte-fwd>
            <mbyte-orig>0</mbyte-orig>
            <mbyte-consumed>0</mbyte-consumed>
            <bpkt-sent>0</bpkt-sent>
            <bpkt-recv>0</bpkt-recv>
            <bpkt-fwd>0</bpkt-fwd>
            <bpkt-orig>0</bpkt-orig>
            <bpkt-consumed>0</bpkt-consumed>
            <bbyte-sent>0</bbyte-sent>
            <bbyte-recv>0</bbyte-recv>
            <bbyte-fwd>0</bbyte-fwd>
            <bbyte-orig>0</bbyte-orig>
            <bbyte-consumed>0</bbyte-consumed>
            <lpkt-sent>0</lpkt-sent>
            <lpkt-recv>0</lpkt-recv>
            <lpkt-fwd>0</lpkt-fwd>
            <lpkt-orig>0</lpkt-orig>
            <lpkt-consumed>0</lpkt-consumed>
            <lbyte-sent>0</lbyte-sent>
            <lbyte-recv>0</lbyte-recv>
            <lbyte-fwd>0</lbyte-fwd>
            <lbyte-orig>0</lbyte-orig>
            <lbyte-consumed>0</lbyte-consumed>
           </ROW_intf>
          </TABLE_intf>
          <TABLE_vrf>
           <ROW_vrf>
            <vrf-name-out>default</vrf-name-out>
           </ROW_vrf>
          </TABLE_vrf>
          <TABLE_intf>
           <ROW_intf>
            <intf-name>Ethernet1/46</intf-name>
            <proto-state>up</proto-state>
            <link-state>up</link-state>
            <admin-state>up</admin-state>
            <iod>51</iod>
            <prefix>10.82.28.21</prefix>
            <subnet>10.82.28.20</subnet>
            <masklen>31</masklen>
            <num-addr>1</num-addr>
            <ip-disabled>FALSE</ip-disabled>
            <bcast-addr>255.255.255.255</bcast-addr>
            <num-maddr>0</num-maddr>
            <mtu>1500</mtu>
            <pref>0</pref>
            <tag>65100</tag>
            <proxy-arp>disabled</proxy-arp>
            <lcl-proxy-arp>disabled</lcl-proxy-arp>
            <mrouting>disabled</mrouting>
            <icmp-redirect>enabled</icmp-redirect>
            <dir-bcast>disabled</dir-bcast>
            <ip-unreach>disabled</ip-unreach>
            <port-unreach>enabled</port-unreach>
            <urpf-mode>none</urpf-mode>
            <ip-ls-type>none</ip-ls-type>
            <stats-last-reset>never</stats-last-reset>
            <upkt-sent>577459459</upkt-sent>
            <upkt-recv>877566475</upkt-recv>
            <upkt-fwd>57</upkt-fwd>
            <upkt-orig>577459402</upkt-orig>
            <upkt-consumed>599511278</upkt-consumed>
            <ubyte-sent>42732921478</ubyte-sent>
            <ubyte-recv>47352431194</ubyte-recv>
            <ubyte-fwd>71686</ubyte-fwd>
            <ubyte-orig>42732849792</ubyte-orig>
            <ubyte-consumed>33573291234</ubyte-consumed>
            <mpkt-sent>0</mpkt-sent>
            <mpkt-recv>0</mpkt-recv>
            <mpkt-fwd>0</mpkt-fwd>
            <mpkt-orig>0</mpkt-orig>
            <mpkt-consumed>0</mpkt-consumed>
            <mbyte-sent>0</mbyte-sent>
            <mbyte-recv>0</mbyte-recv>
            <mbyte-fwd>0</mbyte-fwd>
            <mbyte-orig>0</mbyte-orig>
            <mbyte-consumed>0</mbyte-consumed>
            <bpkt-sent>0</bpkt-sent>
            <bpkt-recv>0</bpkt-recv>
            <bpkt-fwd>0</bpkt-fwd>
            <bpkt-orig>0</bpkt-orig>
            <bpkt-consumed>0</bpkt-consumed>
            <bbyte-sent>0</bbyte-sent>
            <bbyte-recv>0</bbyte-recv>
            <bbyte-fwd>0</bbyte-fwd>
            <bbyte-orig>0</bbyte-orig>
            <bbyte-consumed>0</bbyte-consumed>
            <lpkt-sent>0</lpkt-sent>
            <lpkt-recv>0</lpkt-recv>
            <lpkt-fwd>0</lpkt-fwd>
            <lpkt-orig>0</lpkt-orig>
            <lpkt-consumed>0</lpkt-consumed>
            <lbyte-sent>0</lbyte-sent>
            <lbyte-recv>0</lbyte-recv>
            <lbyte-fwd>0</lbyte-fwd>
            <lbyte-orig>0</lbyte-orig>
            <lbyte-consumed>0</lbyte-consumed>
           </ROW_intf>
          </TABLE_intf>
          <TABLE_vrf>
           <ROW_vrf>
            <vrf-name-out>default</vrf-name-out>
           </ROW_vrf>
          </TABLE_vrf>
          <TABLE_intf>
           <ROW_intf>
            <intf-name>Ethernet1/47</intf-name>
            <proto-state>up</proto-state>
            <link-state>up</link-state>
            <admin-state>up</admin-state>
            <iod>52</iod>
            <prefix>10.82.28.25</prefix>
            <subnet>10.82.28.24</subnet>
            <masklen>31</masklen>
            <num-addr>1</num-addr>
            <ip-disabled>FALSE</ip-disabled>
            <bcast-addr>255.255.255.255</bcast-addr>
            <num-maddr>0</num-maddr>
            <mtu>1500</mtu>
            <pref>0</pref>
            <tag>65100</tag>
            <proxy-arp>disabled</proxy-arp>
            <lcl-proxy-arp>disabled</lcl-proxy-arp>
            <mrouting>disabled</mrouting>
            <icmp-redirect>enabled</icmp-redirect>
            <dir-bcast>disabled</dir-bcast>
            <ip-unreach>disabled</ip-unreach>
            <port-unreach>enabled</port-unreach>
            <urpf-mode>none</urpf-mode>
            <ip-ls-type>none</ip-ls-type>
            <stats-last-reset>never</stats-last-reset>
            <upkt-sent>577444087</upkt-sent>
            <upkt-recv>877545540</upkt-recv>
            <upkt-fwd>180</upkt-fwd>
            <upkt-orig>577443907</upkt-orig>
            <upkt-consumed>599431370</upkt-consumed>
            <ubyte-sent>42734293039</ubyte-sent>
            <ubyte-recv>47425727556</ubyte-recv>
            <ubyte-fwd>103948</ubyte-fwd>
            <ubyte-orig>42734189091</ubyte-orig>
            <ubyte-consumed>33568353278</ubyte-consumed>
            <mpkt-sent>0</mpkt-sent>
            <mpkt-recv>0</mpkt-recv>
            <mpkt-fwd>0</mpkt-fwd>
            <mpkt-orig>0</mpkt-orig>
            <mpkt-consumed>0</mpkt-consumed>
            <mbyte-sent>0</mbyte-sent>
            <mbyte-recv>0</mbyte-recv>
            <mbyte-fwd>0</mbyte-fwd>
            <mbyte-orig>0</mbyte-orig>
            <mbyte-consumed>0</mbyte-consumed>
            <bpkt-sent>0</bpkt-sent>
            <bpkt-recv>0</bpkt-recv>
            <bpkt-fwd>0</bpkt-fwd>
            <bpkt-orig>0</bpkt-orig>
            <bpkt-consumed>0</bpkt-consumed>
            <bbyte-sent>0</bbyte-sent>
            <bbyte-recv>0</bbyte-recv>
            <bbyte-fwd>0</bbyte-fwd>
            <bbyte-orig>0</bbyte-orig>
            <bbyte-consumed>0</bbyte-consumed>
            <lpkt-sent>0</lpkt-sent>
            <lpkt-recv>0</lpkt-recv>
            <lpkt-fwd>0</lpkt-fwd>
            <lpkt-orig>0</lpkt-orig>
            <lpkt-consumed>0</lpkt-consumed>
            <lbyte-sent>0</lbyte-sent>
            <lbyte-recv>0</lbyte-recv>
            <lbyte-fwd>0</lbyte-fwd>
            <lbyte-orig>0</lbyte-orig>
            <lbyte-consumed>0</lbyte-consumed>
           </ROW_intf>
          </TABLE_intf>
          <TABLE_vrf>
           <ROW_vrf>
            <vrf-name-out>management</vrf-name-out>
           </ROW_vrf>
          </TABLE_vrf>
          <TABLE_intf>
           <ROW_intf>
            <intf-name>mgmt0</intf-name>
            <proto-state>up</proto-state>
            <link-state>up</link-state>
            <admin-state>up</admin-state>
            <iod>2</iod>
            <prefix>10.82.30.15</prefix>
            <subnet>10.82.30.0</subnet>
            <masklen>24</masklen>
            <num-addr>1</num-addr>
            <ip-disabled>FALSE</ip-disabled>
            <bcast-addr>255.255.255.255</bcast-addr>
            <num-maddr>0</num-maddr>
            <mtu>1500</mtu>
            <pref>0</pref>
            <tag>0</tag>
            <proxy-arp>disabled</proxy-arp>
            <lcl-proxy-arp>disabled</lcl-proxy-arp>
            <mrouting>disabled</mrouting>
            <icmp-redirect>enabled</icmp-redirect>
            <dir-bcast>disabled</dir-bcast>
            <ip-unreach>disabled</ip-unreach>
            <port-unreach>enabled</port-unreach>
            <urpf-mode>none</urpf-mode>
            <ip-ls-type>none</ip-ls-type>
            <stats-last-reset>never</stats-last-reset>
            <upkt-sent>113360001</upkt-sent>
            <upkt-recv>113196368</upkt-recv>
            <upkt-fwd>0</upkt-fwd>
            <upkt-orig>113360001</upkt-orig>
            <upkt-consumed>226392736</upkt-consumed>
            <ubyte-sent>34863619080</ubyte-sent>
            <ubyte-recv>23504289008</ubyte-recv>
            <ubyte-fwd>0</ubyte-fwd>
            <ubyte-orig>34863619080</ubyte-orig>
            <ubyte-consumed>47006327820</ubyte-consumed>
            <mpkt-sent>0</mpkt-sent>
            <mpkt-recv>112254614</mpkt-recv>
            <mpkt-fwd>0</mpkt-fwd>
            <mpkt-orig>0</mpkt-orig>
            <mpkt-consumed>0</mpkt-consumed>
            <mbyte-sent>0</mbyte-sent>
            <mbyte-recv>11225461400</mbyte-recv>
            <mbyte-fwd>0</mbyte-fwd>
            <mbyte-orig>0</mbyte-orig>
            <mbyte-consumed>0</mbyte-consumed>
            <bpkt-sent>0</bpkt-sent>
            <bpkt-recv>0</bpkt-recv>
            <bpkt-fwd>0</bpkt-fwd>
            <bpkt-orig>0</bpkt-orig>
            <bpkt-consumed>0</bpkt-consumed>
            <bbyte-sent>0</bbyte-sent>
            <bbyte-recv>0</bbyte-recv>
            <bbyte-fwd>0</bbyte-fwd>
            <bbyte-orig>0</bbyte-orig>
            <bbyte-consumed>0</bbyte-consumed>
            <lpkt-sent>0</lpkt-sent>
            <lpkt-recv>0</lpkt-recv>
            <lpkt-fwd>0</lpkt-fwd>
            <lpkt-orig>0</lpkt-orig>
            <lpkt-consumed>0</lpkt-consumed>
            <lbyte-sent>0</lbyte-sent>
            <lbyte-recv>0</lbyte-recv>
            <lbyte-fwd>0</lbyte-fwd>
            <lbyte-orig>0</lbyte-orig>
            <lbyte-consumed>0</lbyte-consumed>
           </ROW_intf>
          </TABLE_intf>
          <TABLE_vrf>
           <ROW_vrf>
            <vrf-name-out>IBM-VPC</vrf-name-out>
           </ROW_vrf>
          </TABLE_vrf>
          <TABLE_intf>
           <ROW_intf>
            <intf-name>Vlan653</intf-name>
            <proto-state>up</proto-state>
            <link-state>up</link-state>
            <admin-state>up</admin-state>
            <iod>123</iod>
            <prefix>169.254.0.2</prefix>
            <subnet>169.254.0.0</subnet>
            <masklen>30</masklen>
            <num-addr>1</num-addr>
            <ip-disabled>FALSE</ip-disabled>
            <bcast-addr>255.255.255.255</bcast-addr>
            <num-maddr>0</num-maddr>
            <mtu>1500</mtu>
            <pref>0</pref>
            <tag>65100</tag>
            <proxy-arp>disabled</proxy-arp>
            <lcl-proxy-arp>disabled</lcl-proxy-arp>
            <mrouting>disabled</mrouting>
            <icmp-redirect>disabled</icmp-redirect>
            <dir-bcast>disabled</dir-bcast>
            <ip-unreach>disabled</ip-unreach>
            <port-unreach>enabled</port-unreach>
            <urpf-mode>none</urpf-mode>
            <ip-ls-type>none</ip-ls-type>
            <stats-last-reset>never</stats-last-reset>
            <upkt-sent>289</upkt-sent>
            <upkt-recv>53</upkt-recv>
            <upkt-fwd>25</upkt-fwd>
            <upkt-orig>277</upkt-orig>
            <upkt-consumed>54</upkt-consumed>
            <ubyte-sent>56820</ubyte-sent>
            <ubyte-recv>3424</ubyte-recv>
            <ubyte-fwd>34692</ubyte-fwd>
            <ubyte-orig>22856</ubyte-orig>
            <ubyte-consumed>3724</ubyte-consumed>
            <mpkt-sent>0</mpkt-sent>
            <mpkt-recv>0</mpkt-recv>
            <mpkt-fwd>0</mpkt-fwd>
            <mpkt-orig>0</mpkt-orig>
            <mpkt-consumed>0</mpkt-consumed>
            <mbyte-sent>0</mbyte-sent>
            <mbyte-recv>0</mbyte-recv>
            <mbyte-fwd>0</mbyte-fwd>
            <mbyte-orig>0</mbyte-orig>
            <mbyte-consumed>0</mbyte-consumed>
            <bpkt-sent>0</bpkt-sent>
            <bpkt-recv>0</bpkt-recv>
            <bpkt-fwd>0</bpkt-fwd>
            <bpkt-orig>0</bpkt-orig>
            <bpkt-consumed>0</bpkt-consumed>
            <bbyte-sent>0</bbyte-sent>
            <bbyte-recv>0</bbyte-recv>
            <bbyte-fwd>0</bbyte-fwd>
            <bbyte-orig>0</bbyte-orig>
            <bbyte-consumed>0</bbyte-consumed>
            <lpkt-sent>0</lpkt-sent>
            <lpkt-recv>0</lpkt-recv>
            <lpkt-fwd>0</lpkt-fwd>
            <lpkt-orig>0</lpkt-orig>
            <lpkt-consumed>0</lpkt-consumed>
            <lbyte-sent>0</lbyte-sent>
            <lbyte-recv>0</lbyte-recv>
            <lbyte-fwd>0</lbyte-fwd>
            <lbyte-orig>0</lbyte-orig>
            <lbyte-consumed>0</lbyte-consumed>
           </ROW_intf>
          </TABLE_intf>
          <TABLE_vrf>
           <ROW_vrf>
            <vrf-name-out>IBM-VPC</vrf-name-out>
           </ROW_vrf>
          </TABLE_vrf>
          <TABLE_intf>
           <ROW_intf>
            <intf-name>Vlan902</intf-name>
            <proto-state>up</proto-state>
            <link-state>up</link-state>
            <admin-state>up</admin-state>
            <iod>124</iod>
            <prefix>10.82.29.9</prefix>
            <subnet>10.82.29.8</subnet>
            <masklen>29</masklen>
            <num-addr>1</num-addr>
            <ip-disabled>FALSE</ip-disabled>
            <bcast-addr>255.255.255.255</bcast-addr>
            <num-maddr>0</num-maddr>
            <mtu>1500</mtu>
            <pref>0</pref>
            <tag>65100</tag>
            <proxy-arp>disabled</proxy-arp>
            <lcl-proxy-arp>disabled</lcl-proxy-arp>
            <mrouting>disabled</mrouting>
            <icmp-redirect>disabled</icmp-redirect>
            <dir-bcast>disabled</dir-bcast>
            <ip-unreach>disabled</ip-unreach>
            <port-unreach>enabled</port-unreach>
            <urpf-mode>none</urpf-mode>
            <ip-ls-type>none</ip-ls-type>
            <stats-last-reset>never</stats-last-reset>
            <upkt-sent>466</upkt-sent>
            <upkt-recv>540</upkt-recv>
            <upkt-fwd>440</upkt-fwd>
            <upkt-orig>26</upkt-orig>
            <upkt-consumed>129</upkt-consumed>
            <ubyte-sent>42413</ubyte-sent>
            <ubyte-recv>72416</ubyte-recv>
            <ubyte-fwd>39761</ubyte-fwd>
            <ubyte-orig>2652</ubyte-orig>
            <ubyte-consumed>10836</ubyte-consumed>
            <mpkt-sent>0</mpkt-sent>
            <mpkt-recv>0</mpkt-recv>
            <mpkt-fwd>0</mpkt-fwd>
            <mpkt-orig>0</mpkt-orig>
            <mpkt-consumed>0</mpkt-consumed>
            <mbyte-sent>0</mbyte-sent>
            <mbyte-recv>0</mbyte-recv>
            <mbyte-fwd>0</mbyte-fwd>
            <mbyte-orig>0</mbyte-orig>
            <mbyte-consumed>0</mbyte-consumed>
            <bpkt-sent>0</bpkt-sent>
            <bpkt-recv>0</bpkt-recv>
            <bpkt-fwd>0</bpkt-fwd>
            <bpkt-orig>0</bpkt-orig>
            <bpkt-consumed>0</bpkt-consumed>
            <bbyte-sent>0</bbyte-sent>
            <bbyte-recv>0</bbyte-recv>
            <bbyte-fwd>0</bbyte-fwd>
            <bbyte-orig>0</bbyte-orig>
            <bbyte-consumed>0</bbyte-consumed>
            <lpkt-sent>0</lpkt-sent>
            <lpkt-recv>0</lpkt-recv>
            <lpkt-fwd>0</lpkt-fwd>
            <lpkt-orig>0</lpkt-orig>
            <lpkt-consumed>0</lpkt-consumed>
            <lbyte-sent>0</lbyte-sent>
            <lbyte-recv>0</lbyte-recv>
            <lbyte-fwd>0</lbyte-fwd>
            <lbyte-orig>0</lbyte-orig>
            <lbyte-consumed>0</lbyte-consumed>
           </ROW_intf>
          </TABLE_intf>
          <TABLE_vrf>
           <ROW_vrf>
            <vrf-name-out>MOSAIC</vrf-name-out>
           </ROW_vrf>
          </TABLE_vrf>
          <TABLE_intf>
           <ROW_intf>
            <intf-name>Vlan652</intf-name>
            <proto-state>up</proto-state>
            <link-state>up</link-state>
            <admin-state>up</admin-state>
            <iod>127</iod>
            <prefix>10.82.28.185</prefix>
            <subnet>10.82.28.184</subnet>
            <masklen>30</masklen>
            <num-addr>1</num-addr>
            <ip-disabled>FALSE</ip-disabled>
            <bcast-addr>255.255.255.255</bcast-addr>
            <num-maddr>0</num-maddr>
            <mtu>1500</mtu>
            <pref>0</pref>
            <tag>65100</tag>
            <proxy-arp>disabled</proxy-arp>
            <lcl-proxy-arp>disabled</lcl-proxy-arp>
            <mrouting>disabled</mrouting>
            <icmp-redirect>disabled</icmp-redirect>
            <dir-bcast>disabled</dir-bcast>
            <ip-unreach>disabled</ip-unreach>
            <port-unreach>enabled</port-unreach>
            <urpf-mode>none</urpf-mode>
            <ip-ls-type>none</ip-ls-type>
            <stats-last-reset>never</stats-last-reset>
            <upkt-sent>13126561</upkt-sent>
            <upkt-recv>5</upkt-recv>
            <upkt-fwd>0</upkt-fwd>
            <upkt-orig>13126561</upkt-orig>
            <upkt-consumed>8</upkt-consumed>
            <ubyte-sent>971365626</ubyte-sent>
            <ubyte-recv>396</ubyte-recv>
            <ubyte-fwd>0</ubyte-fwd>
            <ubyte-orig>971365626</ubyte-orig>
            <ubyte-consumed>672</ubyte-consumed>
            <mpkt-sent>0</mpkt-sent>
            <mpkt-recv>0</mpkt-recv>
            <mpkt-fwd>0</mpkt-fwd>
            <mpkt-orig>0</mpkt-orig>
            <mpkt-consumed>0</mpkt-consumed>
            <mbyte-sent>0</mbyte-sent>
            <mbyte-recv>0</mbyte-recv>
            <mbyte-fwd>0</mbyte-fwd>
            <mbyte-orig>0</mbyte-orig>
            <mbyte-consumed>0</mbyte-consumed>
            <bpkt-sent>0</bpkt-sent>
            <bpkt-recv>0</bpkt-recv>
            <bpkt-fwd>0</bpkt-fwd>
            <bpkt-orig>0</bpkt-orig>
            <bpkt-consumed>0</bpkt-consumed>
            <bbyte-sent>0</bbyte-sent>
            <bbyte-recv>0</bbyte-recv>
            <bbyte-fwd>0</bbyte-fwd>
            <bbyte-orig>0</bbyte-orig>
            <bbyte-consumed>0</bbyte-consumed>
            <lpkt-sent>0</lpkt-sent>
            <lpkt-recv>0</lpkt-recv>
            <lpkt-fwd>0</lpkt-fwd>
            <lpkt-orig>0</lpkt-orig>
            <lpkt-consumed>0</lpkt-consumed>
            <lbyte-sent>0</lbyte-sent>
            <lbyte-recv>0</lbyte-recv>
            <lbyte-fwd>0</lbyte-fwd>
            <lbyte-orig>0</lbyte-orig>
            <lbyte-consumed>0</lbyte-consumed>
           </ROW_intf>
          </TABLE_intf>
          <TABLE_vrf>
           <ROW_vrf>
            <vrf-name-out>MOSAIC</vrf-name-out>
           </ROW_vrf>
          </TABLE_vrf>
          <TABLE_intf>
           <ROW_intf>
            <intf-name>Vlan903</intf-name>
            <proto-state>up</proto-state>
            <link-state>up</link-state>
            <admin-state>up</admin-state>
            <iod>128</iod>
            <prefix>10.82.29.17</prefix>
            <subnet>10.82.29.16</subnet>
            <masklen>29</masklen>
            <num-addr>1</num-addr>
            <ip-disabled>FALSE</ip-disabled>
            <bcast-addr>255.255.255.255</bcast-addr>
            <num-maddr>0</num-maddr>
            <mtu>1500</mtu>
            <pref>0</pref>
            <tag>65100</tag>
            <proxy-arp>disabled</proxy-arp>
            <lcl-proxy-arp>disabled</lcl-proxy-arp>
            <mrouting>disabled</mrouting>
            <icmp-redirect>disabled</icmp-redirect>
            <dir-bcast>disabled</dir-bcast>
            <ip-unreach>disabled</ip-unreach>
            <port-unreach>enabled</port-unreach>
            <urpf-mode>none</urpf-mode>
            <ip-ls-type>none</ip-ls-type>
            <stats-last-reset>never</stats-last-reset>
            <upkt-sent>0</upkt-sent>
            <upkt-recv>0</upkt-recv>
            <upkt-fwd>0</upkt-fwd>
            <upkt-orig>0</upkt-orig>
            <upkt-consumed>0</upkt-consumed>
            <ubyte-sent>0</ubyte-sent>
            <ubyte-recv>0</ubyte-recv>
            <ubyte-fwd>0</ubyte-fwd>
            <ubyte-orig>0</ubyte-orig>
            <ubyte-consumed>0</ubyte-consumed>
            <mpkt-sent>0</mpkt-sent>
            <mpkt-recv>0</mpkt-recv>
            <mpkt-fwd>0</mpkt-fwd>
            <mpkt-orig>0</mpkt-orig>
            <mpkt-consumed>0</mpkt-consumed>
            <mbyte-sent>0</mbyte-sent>
            <mbyte-recv>0</mbyte-recv>
            <mbyte-fwd>0</mbyte-fwd>
            <mbyte-orig>0</mbyte-orig>
            <mbyte-consumed>0</mbyte-consumed>
            <bpkt-sent>0</bpkt-sent>
            <bpkt-recv>0</bpkt-recv>
            <bpkt-fwd>0</bpkt-fwd>
            <bpkt-orig>0</bpkt-orig>
            <bpkt-consumed>0</bpkt-consumed>
            <bbyte-sent>0</bbyte-sent>
            <bbyte-recv>0</bbyte-recv>
            <bbyte-fwd>0</bbyte-fwd>
            <bbyte-orig>0</bbyte-orig>
            <bbyte-consumed>0</bbyte-consumed>
            <lpkt-sent>0</lpkt-sent>
            <lpkt-recv>0</lpkt-recv>
            <lpkt-fwd>0</lpkt-fwd>
            <lpkt-orig>0</lpkt-orig>
            <lpkt-consumed>0</lpkt-consumed>
            <lbyte-sent>0</lbyte-sent>
            <lbyte-recv>0</lbyte-recv>
            <lbyte-fwd>0</lbyte-fwd>
            <lbyte-orig>0</lbyte-orig>
            <lbyte-consumed>0</lbyte-consumed>
           </ROW_intf>
          </TABLE_intf>
          <TABLE_vrf>
           <ROW_vrf>
            <vrf-name-out>INET</vrf-name-out>
           </ROW_vrf>
          </TABLE_vrf>
          <TABLE_intf>
           <ROW_intf>
            <intf-name>Vlan3900</intf-name>
            <proto-state>up</proto-state>
            <link-state>up</link-state>
            <admin-state>up</admin-state>
            <iod>131</iod>
            <prefix>12.151.180.169</prefix>
            <subnet>12.151.180.168</subnet>
            <masklen>29</masklen>
            <num-addr>1</num-addr>
            <ip-disabled>FALSE</ip-disabled>
            <bcast-addr>255.255.255.255</bcast-addr>
            <num-maddr>0</num-maddr>
            <mtu>1500</mtu>
            <pref>0</pref>
            <tag>0</tag>
            <proxy-arp>disabled</proxy-arp>
            <lcl-proxy-arp>disabled</lcl-proxy-arp>
            <mrouting>disabled</mrouting>
            <icmp-redirect>disabled</icmp-redirect>
            <dir-bcast>disabled</dir-bcast>
            <ip-unreach>disabled</ip-unreach>
            <port-unreach>enabled</port-unreach>
            <urpf-mode>none</urpf-mode>
            <ip-ls-type>none</ip-ls-type>
            <stats-last-reset>never</stats-last-reset>
            <upkt-sent>2257</upkt-sent>
            <upkt-recv>66</upkt-recv>
            <upkt-fwd>2178</upkt-fwd>
            <upkt-orig>79</upkt-orig>
            <upkt-consumed>1212332</upkt-consumed>
            <ubyte-sent>358056</ubyte-sent>
            <ubyte-recv>5577</ubyte-recv>
            <ubyte-fwd>350110</ubyte-fwd>
            <ubyte-orig>7946</ubyte-orig>
            <ubyte-consumed>100402808</ubyte-consumed>
            <mpkt-sent>0</mpkt-sent>
            <mpkt-recv>0</mpkt-recv>
            <mpkt-fwd>0</mpkt-fwd>
            <mpkt-orig>0</mpkt-orig>
            <mpkt-consumed>0</mpkt-consumed>
            <mbyte-sent>0</mbyte-sent>
            <mbyte-recv>0</mbyte-recv>
            <mbyte-fwd>0</mbyte-fwd>
            <mbyte-orig>0</mbyte-orig>
            <mbyte-consumed>0</mbyte-consumed>
            <bpkt-sent>0</bpkt-sent>
            <bpkt-recv>5</bpkt-recv>
            <bpkt-fwd>0</bpkt-fwd>
            <bpkt-orig>0</bpkt-orig>
            <bpkt-consumed>0</bpkt-consumed>
            <bbyte-sent>0</bbyte-sent>
            <bbyte-recv>396</bbyte-recv>
            <bbyte-fwd>0</bbyte-fwd>
            <bbyte-orig>0</bbyte-orig>
            <bbyte-consumed>0</bbyte-consumed>
            <lpkt-sent>0</lpkt-sent>
            <lpkt-recv>0</lpkt-recv>
            <lpkt-fwd>0</lpkt-fwd>
            <lpkt-orig>0</lpkt-orig>
            <lpkt-consumed>0</lpkt-consumed>
            <lbyte-sent>0</lbyte-sent>
            <lbyte-recv>0</lbyte-recv>
            <lbyte-fwd>0</lbyte-fwd>
            <lbyte-orig>0</lbyte-orig>
            <lbyte-consumed>0</lbyte-consumed>
           </ROW_intf>
          </TABLE_intf>
          <TABLE_vrf>
           <ROW_vrf>
            <vrf-name-out>INET</vrf-name-out>
           </ROW_vrf>
          </TABLE_vrf>
          <TABLE_intf>
           <ROW_intf>
            <intf-name>Ethernet1/27</intf-name>
            <proto-state>up</proto-state>
            <link-state>up</link-state>
            <admin-state>up</admin-state>
            <iod>32</iod>
            <prefix>12.117.212.34</prefix>
            <subnet>12.117.212.32</subnet>
            <masklen>30</masklen>
            <num-addr>1</num-addr>
            <ip-disabled>FALSE</ip-disabled>
            <bcast-addr>255.255.255.255</bcast-addr>
            <num-maddr>0</num-maddr>
            <mtu>1500</mtu>
            <pref>0</pref>
            <tag>0</tag>
            <proxy-arp>disabled</proxy-arp>
            <lcl-proxy-arp>disabled</lcl-proxy-arp>
            <mrouting>disabled</mrouting>
            <icmp-redirect>enabled</icmp-redirect>
            <dir-bcast>disabled</dir-bcast>
            <ip-unreach>disabled</ip-unreach>
            <port-unreach>enabled</port-unreach>
            <urpf-mode>none</urpf-mode>
            <ip-ls-type>none</ip-ls-type>
            <stats-last-reset>never</stats-last-reset>
            <upkt-sent>1731233</upkt-sent>
            <upkt-recv>6360071</upkt-recv>
            <upkt-fwd>0</upkt-fwd>
            <upkt-orig>1731233</upkt-orig>
            <upkt-consumed>4353574</upkt-consumed>
            <ubyte-sent>171837990</ubyte-sent>
            <ubyte-recv>421418476</ubyte-recv>
            <ubyte-fwd>0</ubyte-fwd>
            <ubyte-orig>171837990</ubyte-orig>
            <ubyte-consumed>362701547</ubyte-consumed>
            <mpkt-sent>0</mpkt-sent>
            <mpkt-recv>0</mpkt-recv>
            <mpkt-fwd>0</mpkt-fwd>
            <mpkt-orig>0</mpkt-orig>
            <mpkt-consumed>0</mpkt-consumed>
            <mbyte-sent>0</mbyte-sent>
            <mbyte-recv>0</mbyte-recv>
            <mbyte-fwd>0</mbyte-fwd>
            <mbyte-orig>0</mbyte-orig>
            <mbyte-consumed>0</mbyte-consumed>
            <bpkt-sent>0</bpkt-sent>
            <bpkt-recv>0</bpkt-recv>
            <bpkt-fwd>0</bpkt-fwd>
            <bpkt-orig>0</bpkt-orig>
            <bpkt-consumed>0</bpkt-consumed>
            <bbyte-sent>0</bbyte-sent>
            <bbyte-recv>0</bbyte-recv>
            <bbyte-fwd>0</bbyte-fwd>
            <bbyte-orig>0</bbyte-orig>
            <bbyte-consumed>0</bbyte-consumed>
            <lpkt-sent>0</lpkt-sent>
            <lpkt-recv>0</lpkt-recv>
            <lpkt-fwd>0</lpkt-fwd>
            <lpkt-orig>0</lpkt-orig>
            <lpkt-consumed>0</lpkt-consumed>
            <lbyte-sent>0</lbyte-sent>
            <lbyte-recv>0</lbyte-recv>
            <lbyte-fwd>0</lbyte-fwd>
            <lbyte-orig>0</lbyte-orig>
            <lbyte-consumed>0</lbyte-consumed>
           </ROW_intf>
          </TABLE_intf>
         </__readonly__>
        </__XML__OPT_Cmd_ip_show_interface_command___readonly__>
       </__XML__OPT_Cmd_ip_show_interface_command_vrf>
      </__XML__OPT_Cmd_ip_show_interface_command_operational>
     </__XML__BLK_Cmd_ip_show_interface_command_brief>
    </interface>
   </ip>
  </show>
 </nf:data>
</nf:rpc-reply>